Metadata-Version: 1.0
Name: xxxfree
Version: 2.0.0
Summary: 这是我的一个库
Home-page: UNKNOWN
Author: free
Author-email: 835574039@qq.com
License: UNKNOWN
Platform: UNKNOWN
